easytag/__init__.py
easytag/tagSearch.py
easytag-0.0.3.dist-info/DESCRIPTION.rst
easytag-0.0.3.dist-info/METADATA
easytag-0.0.3.dist-info/RECORD
easytag-0.0.3.dist-info/WHEEL
easytag-0.0.3.dist-info/entry_points.txt
easytag-0.0.3.dist-info/metadata.json
easytag-0.0.3.dist-info/top_level.txt
